muss/__init__.py
muss-0.2.2.dist-info/LICENSE
muss-0.2.2.dist-info/METADATA
muss-0.2.2.dist-info/WHEEL
muss-0.2.2.dist-info/top_level.txt
muss-0.2.2.dist-info/RECORD
